{
  "data": {
    "Металлокассеты": {
      "Металлокассета фасадная": {
        "coefficient": 1,
        "price": 870
      },
      "П-профиль": {
        "coefficient": 1.8,
        "price": 92.44
      },
      "Г-профиль": {
        "coefficient": 1.4,
        "price": 54.56
      },
      "Кронштейн": {
        "coefficient": 3.85,
        "price": 8.64
      },
      "Прокладка терморазрывная для кронштейнов": {
        "coefficient": 3.85,
        "price": 2.5
      },
      "Анкерный болт": {
        "coefficient": 3.85,
        "price": 12
      },
      "Саморез фасадный шестигранный": {
        "coefficient": 12,
        "price": 1.3
      }
    },
    "Композит": {
      "Профиль вертикальный усиленный": {
        "coefficient": 1,
        "price": 133.18
      },
      "Стеновой кронштейн": {
        "coefficient": 0.9,
        "price": 41.18
      },
      "Прокладка терморазрывная для стенового кронштейна": {
        "coefficient": 0.9,
        "price": 6.4
      },
      "Икля": {
        "coefficient": 3.6,
        "price": 25.71
      },
      "Салазка": {
        "coefficient": 1.8,
        "price": 36.94
      },
      "Угловой кронштейн": {
        "coefficient": 0.08,
        "price": 156.66
      },
      "Прокладка терморазрывная для углового кронштейна": {
        "coefficient": 0.08,
        "price": 18.7
      },
      "Профиль угловой": {
        "coefficient": 0.05,
        "price": 66.75
      }
    },
    "Керамогранит": {
      "Профиль вертикальный усиленный": {
        "coefficient": 2,
        "price": 293.57
      },
      "Стеновой кронштейн": {
        "coefficient": 0.7,
        "price": 167.53
      },
      "Прокладка терморазрывная для стенового кронштейна": {
        "coefficient": 1.4,
        "price": 8
      },
      "Кляммер основной для керам-та": {
        "coefficient": 3.21,
        "price": 29.82
      },
      "Кляммер стартовый для керам-та": {
        "coefficient": 0.75,
        "price": 21.08
      }
    },
    "Фиброплита": {
      "П-профиль": {
        "coefficient": 1.8,
        "price": 77.5
      },
      "Г-профиль": {
        "coefficient": 1.4,
        "price": 47.12
      },
      "Прокладка терморазрывная для кронштейнов": {
        "coefficient": 3.75,
        "price": 1.62
      },
      "Анкерный болт": {
        "coefficient": 3.75,
        "price": 10.6
      },
      "Кронштейн усиленный": {
        "coefficient": 3.75,
        "price": 10.42
      },
      "Саморез фасадный шестигранный": {
        "coefficient": 8,
        "price": 1.2
      }
    }
  }
}